omegapy/__init__.py
omegapy/omega_data.py
omegapy/omega_plots.py
omegapy/package.json
omegapy/useful_functions.py
omegapy/OMEGA_dataref/OBC_OMEGA_OCT2017.sav
omegapy/OMEGA_dataref/boundcur.dat
omegapy/OMEGA_dataref/corrupted_obs.csv
omegapy/OMEGA_dataref/cubindex.ref
omegapy/OMEGA_dataref/flatVIS050701.bin
omegapy/OMEGA_dataref/fond2.dat
omegapy/OMEGA_dataref/lambda_0403.dat
omegapy/OMEGA_dataref/linearC.dat
omegapy/OMEGA_dataref/mtf120315_25.dat
omegapy/OMEGA_dataref/mtf120315_50.dat
omegapy/OMEGA_dataref/omega128_interpol.sav
omegapy/OMEGA_dataref/omega_atmorap_CL.dat
omegapy/OMEGA_dataref/omega_wvl_CL.dat
omegapy/OMEGA_dataref/rapcur_25.dat
omegapy/OMEGA_dataref/rapcur_50.dat
omegapy/OMEGA_dataref/rapmtflcur.bin
omegapy/OMEGA_dataref/refclair_sombr_omega_CL.dat
omegapy/OMEGA_dataref/specsol_0403.dat
omegapy/res_findcube/cubelist
omegapy-3.2.1.dist-info/licenses/LICENSE
omegapy-3.2.1.dist-info/METADATA
omegapy-3.2.1.dist-info/WHEEL
omegapy-3.2.1.dist-info/top_level.txt
omegapy-3.2.1.dist-info/RECORD
