Metadata-Version: 2.4
Name: omegapy
Version: 3.2.1
Summary: Python tools for OMEGA/MEx observations analysis
Home-page: https://astcherbinine.github.io/omegapy
Author: Aurélien Stcherbinine
Author-email: aurelien@stcherbinine.net
Project-URL: Source, https://github.com/AStcherbinine/omegapy
Classifier: Programming Language :: Python :: 3
Classifier: License :: OSI Approved :: MIT License
Classifier: Operating System :: OS Independent
Classifier: Intended Audience :: Science/Research
Classifier: Topic :: Scientific/Engineering :: Astronomy
Requires-Python: >=3.7
License-File: LICENSE
Requires-Dist: numpy>=1.17
Requires-Dist: matplotlib>=3.0
Requires-Dist: tqdm>=4.31
Requires-Dist: scipy>=1.3
Requires-Dist: pandas>=0.25
Dynamic: author
Dynamic: author-email
Dynamic: classifier
Dynamic: description
Dynamic: description-content-type
Dynamic: home-page
Dynamic: license-file
Dynamic: project-url
Dynamic: requires-dist
Dynamic: requires-python
Dynamic: summary
